zero_mech/__init__.py
zero_mech/active.py
zero_mech/atoms.py
zero_mech/compressibility.py
zero_mech/experiments.py
zero_mech/material.py
zero_mech/model.py
zero_mech/viscosity.py
zero_mech-0.1.2.dist-info/LICENSE
zero_mech-0.1.2.dist-info/METADATA
zero_mech-0.1.2.dist-info/WHEEL
zero_mech-0.1.2.dist-info/entry_points.txt
zero_mech-0.1.2.dist-info/top_level.txt
zero_mech-0.1.2.dist-info/RECORD
